pyspextools/__init__.py
pyspextools/color.py
pyspextools/messages.py
pyspextools/data/__init__.py
pyspextools/data/badchannels.py
pyspextools/data/response.py
pyspextools/io/__init__.py
pyspextools/io/arf.py
pyspextools/io/convert.py
pyspextools/io/dataset.py
pyspextools/io/ogip.py
pyspextools/io/pha.py
pyspextools/io/pha2.py
pyspextools/io/region.py
pyspextools/io/res.py
pyspextools/io/rmf.py
pyspextools/io/spo.py
pyspextools/io/tg.py
pyspextools/model/__init__.py
pyspextools/model/user.py
pyspextools-0.4.0.data/scripts/ogip2spex
pyspextools-0.4.0.data/scripts/ogipgenrsp
pyspextools-0.4.0.data/scripts/simres
pyspextools-0.4.0.data/scripts/tg2spex
pyspextools-0.4.0.dist-info/LICENSE.txt
pyspextools-0.4.0.dist-info/METADATA
pyspextools-0.4.0.dist-info/NOTICE
pyspextools-0.4.0.dist-info/WHEEL
pyspextools-0.4.0.dist-info/top_level.txt
pyspextools-0.4.0.dist-info/RECORD
