Metadata-Version: 2.1
Name: pyspextools
Version: 0.4.0
Summary: SPEX Python tools
Home-page: https://github.com/spex-xray/pyspextools
Author: SPEX development team
Author-email: j.de.plaa@sron.nl
License: Apache 2.0
Platform: UNKNOWN
Requires-Dist: future (>=0.15)
Requires-Dist: numpy (>=1.11)
Requires-Dist: astropy (>=1.1)
Requires-Dist: sphinx-argparse (>=0.1.15)
Requires-Dist: sphinx
